AUTHORS.rst
CONTRIBUTING.rst
HISTORY.rst
LICENSE
MANIFEST.in
README.rst
setup.cfg
setup.py
docs/Makefile
docs/authors.rst
docs/conf.py
docs/contributing.rst
docs/history.rst
docs/index.rst
docs/installation.rst
docs/make.bat
docs/readme.rst
docs/usage.rst
myratings/__init__.py
myratings/cli.py
myratings/codechef.py
myratings/codeforces.py
myratings/hackerearth.py
myratings/hackerrank.py
myratings/judges.py
myratings/myratings.py
myratings/scrape.py
myratings/topcoder.py
myratings.egg-info/PKG-INFO
myratings.egg-info/SOURCES.txt
myratings.egg-info/dependency_links.txt
myratings.egg-info/entry_points.txt
myratings.egg-info/not-zip-safe
myratings.egg-info/requires.txt
myratings.egg-info/top_level.txt
tests/__init__.py
tests/test_myratings.py