Metadata-Version: 1.2
Name: myratings
Version: 1.2.2
Summary: Displays ratings of the user from various competitive programming sites in the terminal !!
Home-page: https://github.com/kgarun/myratings
Author: Arun KG
Author-email: kgarun50@gmail.com
License: MIT license
Keywords: myratings competitive programming cp terminal rating ratings
Platform: UNKNOWN
Classifier: Development Status :: 4 - Beta
Classifier: Intended Audience :: Developers
Classifier: Intended Audience :: End Users/Desktop
Classifier: License :: OSI Approved :: MIT License
Classifier: Natural Language :: English
Classifier: Topic :: Terminals
Classifier: Programming Language :: Python :: 3
Classifier: Programming Language :: Python :: 3.3
Classifier: Programming Language :: Python :: 3.5
Requires-Python: >=3
